Metadata-Version: 2.1
Name: qaquora
Version: 0.2
Summary: This is a python package to extra all questions and answers related to any topic on quora
Home-page: UNKNOWN
Author: Yugal Jain
License: UNKNOWN
Platform: UNKNOWN
